pydal/__init__.py
pydal/_compat.py
pydal/_globals.py
pydal/_load.py
pydal/base.py
pydal/connection.py
pydal/default_validators.py
pydal/drivers.py
pydal/exceptions.py
pydal/migrator.py
pydal/objects.py
pydal/querybuilder.py
pydal/restapi.py
pydal/utils.py
pydal/validators.py
pydal/adapters/__init__.py
pydal/adapters/base.py
pydal/adapters/couchdb.py
pydal/adapters/db2.py
pydal/adapters/firebird.py
pydal/adapters/google.py
pydal/adapters/informix.py
pydal/adapters/ingres.py
pydal/adapters/mongo.py
pydal/adapters/mssql.py
pydal/adapters/mysql.py
pydal/adapters/oracle.py
pydal/adapters/postgres.py
pydal/adapters/sap.py
pydal/adapters/snowflake.py
pydal/adapters/sqlite.py
pydal/adapters/teradata.py
pydal/contrib/__init__.py
pydal/contrib/imap_adapter.py
pydal/contrib/ipaddress.py
pydal/contrib/mockimaplib.py
pydal/contrib/ordereddict.py
pydal/contrib/portalocker.py
pydal/contrib/reserved_sql_keywords.py
pydal/dialects/__init__.py
pydal/dialects/base.py
pydal/dialects/couchdb.py
pydal/dialects/db2.py
pydal/dialects/firebird.py
pydal/dialects/google.py
pydal/dialects/informix.py
pydal/dialects/ingres.py
pydal/dialects/mongo.py
pydal/dialects/mssql.py
pydal/dialects/mysql.py
pydal/dialects/oracle.py
pydal/dialects/postgre.py
pydal/dialects/sap.py
pydal/dialects/snowflake.py
pydal/dialects/sqlite.py
pydal/dialects/teradata.py
pydal/helpers/__init__.py
pydal/helpers/_internals.py
pydal/helpers/classes.py
pydal/helpers/methods.py
pydal/helpers/regex.py
pydal/helpers/rest.py
pydal/helpers/serializers.py
pydal/parsers/__init__.py
pydal/parsers/base.py
pydal/parsers/google.py
pydal/parsers/mongo.py
pydal/parsers/oracle.py
pydal/parsers/postgre.py
pydal/parsers/sqlite.py
pydal/representers/__init__.py
pydal/representers/base.py
pydal/representers/couchdb.py
pydal/representers/db2.py
pydal/representers/google.py
pydal/representers/informix.py
pydal/representers/mongo.py
pydal/representers/mssql.py
pydal/representers/mysql.py
pydal/representers/oracle.py
pydal-20260118.1.dist-info/licenses/AUTHORS
pydal-20260118.1.dist-info/licenses/LICENSE.txt
pydal-20260118.1.dist-info/METADATA
pydal-20260118.1.dist-info/WHEEL
pydal-20260118.1.dist-info/top_level.txt
pydal-20260118.1.dist-info/RECORD
