Metadata-Version: 2.4
Name: pydal
Version: 20260118.1
Summary: pyDAL is a Database Abstraction Layer. It generates queries for SQlite, PotsgreSQL, MySQL, and other backends. It was originally part of the web2py frameworks but it is now an independent project. Example: db.define_table("thing",Field("name")) and db.thing.insert(name="Pizza")
Author-email: Massimo Di Pierro <massimo.dipierro@gmail.com>
Project-URL: Homepage, https://github.com/web2py/pydal
Project-URL: Bug Tracker, https://github.com/web2py/pydal/issues
Project-URL: Documentation, https://py4web.com/_documentation/static/en/chapter-07.html
Classifier: Programming Language :: Python :: 3
Classifier: License :: OSI Approved :: BSD License
Classifier: Operating System :: OS Independent
Requires-Python: >=3.7
License-File: LICENSE.txt
License-File: AUTHORS
Provides-Extra: test
Requires-Dist: legacy-cgi; python_version >= "3.13" and extra == "test"
Provides-Extra: manage
Requires-Dist: twine; extra == "manage"
Dynamic: license-file
